[
  {
    "newsName": "연합뉴스",
    "newsLink": "https://news.naver.com/main/list.naver?mode=LPOD&mid=sec&sid1=001&sid2=140&oid=001&isYeonhapFlash=Y",
    "contentsHeader": "복지장관-전공의 비공개 만남…'전문의' 중심으로 병원 전환",
    "contentsLink": "https://news.naver.com/main/list.naver?mode=LPOD&mid=sec&sid1=001&sid2=140&oid=001&isYeonhapFlash=Y&aid=0014557974"
  },
  {
    "newsName": "연합뉴스",
    "newsLink": "https://news.naver.com/main/list.naver?mode=LPOD&mid=sec&sid1=001&sid2=140&oid=001&isYeonhapFlash=Y",
    "contentsHeader": "의협 \"교수에 진료유지명령 내리면 의료시스템 존립 불가능할것\"",
    "contentsLink": "https://news.naver.com/main/list.naver?mode=LPOD&mid=sec&sid1=001&sid2=140&oid=001&isYeonhapFlash=Y&aid=0014558087"
  },
  {
    "newsName": "연합뉴스",
    "newsLink": "https://news.naver.com/main/list.naver?mode=LPOD&mid=sec&sid1=001&sid2=140&oid=001&isYeonhapFlash=Y",
    "contentsHeader": "與현역 한기호·강대식·김형동·이용 경선승리…하태경 낙천",
    "contentsLink": "https://news.naver.com/main/list.naver?mode=LPOD&mid=sec&sid1=001&sid2=140&oid=001&isYeonhapFlash=Y&aid=0014558054"
  },
  {
    "newsName": "연합뉴스",
    "newsLink": "https://news.naver.com/main/list.naver?mode=LPOD&mid=sec&sid1=001&sid2=140&oid=001&isYeonhapFlash=Y",
    "contentsHeader": "與선대위 한동훈 총괄…나경원 안철수 원희룡 윤재옥 공동체제",
    "contentsLink": "https://news.naver.com/main/list.naver?mode=LPOD&mid=sec&sid1=001&sid2=140&oid=001&isYeonhapFlash=Y&aid=0014558025"
  },
  {
    "newsName": "연합뉴스",
    "newsLink": "https://news.naver.com/main/list.naver?mode=LPOD&mid=sec&sid1=001&sid2=140&oid=001&isYeonhapFlash=Y",
    "contentsHeader": "한국 선교사 간첩 혐의 체포…악화일로 한러관계에 새 악재",
    "contentsLink": "https://news.naver.com/main/list.naver?mode=LPOD&mid=sec&sid1=001&sid2=140&oid=001&isYeonhapFlash=Y&aid=0014557918"
  },
  {
    "newsName": "연합뉴스",
    "newsLink": "https://news.naver.com/main/list.naver?mode=LPOD&mid=sec&sid1=001&sid2=140&oid=001&isYeonhapFlash=Y",
    "contentsHeader": "\"삼성·SK하이닉스, 반도체 노후장비 판매중단…美압박 의식\"",
    "contentsLink": "https://news.naver.com/main/list.naver?mode=LPOD&mid=sec&sid1=001&sid2=140&oid=001&isYeonhapFlash=Y&aid=0014557784"
  },
  {
    "newsName": "연합뉴스",
    "newsLink": "https://news.naver.com/main/list.naver?mode=LPOD&mid=sec&sid1=001&sid2=140&oid=001&isYeonhapFlash=Y",
    "contentsHeader": "민주, 위성정당 비례대표 후보로 백승아·위성락 등 20명 추천",
    "contentsLink": "https://news.naver.com/main/list.naver?mode=LPOD&mid=sec&sid1=001&sid2=140&oid=001&isYeonhapFlash=Y&aid=0014557624"
  },
  {
    "newsName": "연합뉴스",
    "newsLink": "https://news.naver.com/main/list.naver?mode=LPOD&mid=sec&sid1=001&sid2=140&oid=001&isYeonhapFlash=Y",
    "contentsHeader": "공수처 \"이종섭 추가 조사 반드시 필요…소환조사가 원칙\"",
    "contentsLink": "https://news.naver.com/main/list.naver?mode=LPOD&mid=sec&sid1=001&sid2=140&oid=001&isYeonhapFlash=Y&aid=0014557600"
  },
  {
    "newsName": "연합뉴스",
    "newsLink": "https://news.naver.com/main/list.naver?mode=LPOD&mid=sec&sid1=001&sid2=140&oid=001&isYeonhapFlash=Y",
    "contentsHeader": "인센티브 줬다고 연차수당 '꿀꺽'…청년 근로자 울린 기업들",
    "contentsLink": "https://news.naver.com/main/list.naver?mode=LPOD&mid=sec&sid1=001&sid2=140&oid=001&isYeonhapFlash=Y&aid=0014557570"
  },
  {
    "newsName": "연합뉴스",
    "newsLink": "https://news.naver.com/main/list.naver?mode=LPOD&mid=sec&sid1=001&sid2=140&oid=001&isYeonhapFlash=Y",
    "contentsHeader": "서울의대 교수비대위, '의사 증원 1년후 결정·대화협의체' 제안",
    "contentsLink": "https://news.naver.com/main/list.naver?mode=LPOD&mid=sec&sid1=001&sid2=140&oid=001&isYeonhapFlash=Y&aid=0014557554"
  }
]
